xarm/__init__.py
xarm/tasks/__init__.py
xarm/tasks/assets/lift.xml
xarm/tasks/assets/mesh/base_link.stl
xarm/tasks/assets/mesh/block_inner.stl
xarm/tasks/assets/mesh/block_inner2.stl
xarm/tasks/assets/mesh/block_outer.stl
xarm/tasks/assets/mesh/left_finger.stl
xarm/tasks/assets/mesh/left_inner_knuckle.stl
xarm/tasks/assets/mesh/left_outer_knuckle.stl
xarm/tasks/assets/mesh/link1.stl
xarm/tasks/assets/mesh/link2.stl
xarm/tasks/assets/mesh/link3.stl
xarm/tasks/assets/mesh/link4.stl
xarm/tasks/assets/mesh/link5.stl
xarm/tasks/assets/mesh/link6.stl
xarm/tasks/assets/mesh/link7.stl
xarm/tasks/assets/mesh/link_base.stl
xarm/tasks/assets/mesh/right_finger.stl
xarm/tasks/assets/mesh/right_inner_knuckle.stl
xarm/tasks/assets/mesh/right_outer_knuckle.stl
xarm/tasks/assets/peg_in_box.xml
xarm/tasks/assets/push.xml
xarm/tasks/assets/reach.xml
xarm/tasks/assets/shared.xml
xarm/tasks/assets/xarm.xml
xarm/tasks/base.py
xarm/tasks/lift.py
xarm/tasks/mocap.py
xarm/tasks/peg_in_box.py
xarm/tasks/push.py
xarm/tasks/reach.py
sim_xarm-0.1.0.dist-info/METADATA
sim_xarm-0.1.0.dist-info/WHEEL
sim_xarm-0.1.0.dist-info/RECORD
