Metadata-Version: 2.1
Name: sim_xarm
Version: 0.1.0
Summary: xArm environment for LeRobot
License: Apache-2.0
Author: Rémi Cadène
Author-email: re.cadene@gmail.com
Maintainer: Alexander Soare
Maintainer-email: alexander.soare159@gmail.com
Requires-Python: >=3.10,<4.0
Classifier: Development Status :: 3 - Alpha
Classifier: Intended Audience :: Developers
Classifier: License :: OSI Approved :: Apache Software License
Classifier: Programming Language :: Python :: 3
Classifier: Programming Language :: Python :: 3.10
Classifier: Programming Language :: Python :: 3.11
Classifier: Programming Language :: Python :: 3.12
Classifier: Topic :: Software Development :: Build Tools
Requires-Dist: gymnasium (>=0.29.1,<0.30.0)
Requires-Dist: gymnasium-robotics (>=1.2.4,<2.0.0)
Requires-Dist: mujoco (>=2.3.7,<3.0.0)
